LICENSE
MANIFEST.in
README.rst
setup.py
scipion_em_simple.egg-info/PKG-INFO
scipion_em_simple.egg-info/SOURCES.txt
scipion_em_simple.egg-info/dependency_links.txt
scipion_em_simple.egg-info/top_level.txt
simple/__init__.py
simple/bibtex.py
simple/constants.py
simple/protocols.conf
simple/simple_logo.png
simple/protocols/__init__.py
simple/protocols/protocol_prime.py
simple/tests/__init__.py
simple/tests/test_workflow_simple.py