Metadata-Version: 1.1
Name: scipion-em-simple
Version: 1.0.3
Summary: Plugin to use Simple programs within the Scipion framework
Home-page: https://github.com/scipion-em/scipion-em-simple
Author: I2PC
Author-email: scipion@cnb.csic.es
License: UNKNOWN
Keywords: scipion electron-microscopy cryo-em structural-biology image-processing
Platform: UNKNOWN
Classifier: Development Status :: 4 - Beta
Classifier: License :: OSI Approved :: GNU General Public License v3 (GPLv3)
Classifier: Programming Language :: Python :: 2.7
